{
    "sections": [
        {
            "title": "Getting Started",
            "items": [
                {
                    "title": "Installation",
                    "path": "installation.md"
                },
                {
                    "title": "Configuration",
                    "path": "config.md"
                },
                {
                    "title": "Auto Localization",
                    "path": "auto-localization.md"
                }
            ]
        },
        {
            "title": "Core Features",
            "items": [
                {
                    "title": "Lists",
                    "path": "listings.md"
                },
                {
                    "title": "Forms",
                    "path": "forms.md"
                },
                {
                    "title": "Actions",
                    "path": "actions.md"
                },
                {
                    "title": "Widgets",
                    "path": "widgets.md"
                }
            ]
        },
        {
            "title": "Panels",
            "items": [
                {
                    "title": "Overview",
                    "path": "panels.md"
                },
                {
                    "title": "Layout Components",
                    "path": "layouts.md"
                }
            ]
        },
        {
            "title": "Frontend",
            "items": [
                {
                    "title": "Theming",
                    "path": "theming.md"
                },
                {
                    "title": "Modals",
                    "path": "modals.md"
                },
                {
                    "title": "Toasts",
                    "path": "toasts.md"
                }
            ]
        }
    ]
}
